Metadata-Version: 2.1
Name: WorldOfGamesDEC
Version: 1.3.4
Summary: World of Games by Mike Joseph
Home-page: https://github.com/justmike1/WorldOfGames-DEC
Author: Mike Joseph
Author-email: mikeyusufov@gmail.com
License: MIT
Project-URL: Bug Tracker, https://github.com/justmike1/WorldOfGames-DEC/issues
Platform: UNKNOWN
